grapevne/__init__.py
grapevne/defs.py
grapevne/grapevne.py
grapevne/utils.py
grapevne/version.py
grapevne/helpers/__init__.py
grapevne/helpers/helpers.py
grapevne-0.2.5.dist-info/LICENSE
grapevne-0.2.5.dist-info/METADATA
grapevne-0.2.5.dist-info/WHEEL
grapevne-0.2.5.dist-info/top_level.txt
grapevne-0.2.5.dist-info/RECORD
