Metadata-Version: 2.1
Name: grapevne
Version: 0.2.5
Summary: Python library for grapevne snakemake support
Requires-Python: >=3.9
License-File: LICENSE
Requires-Dist: packaging>=24.1
